{
  "buildCommand" : {
    "command" : "build",
    "skipDependencies" : false,
    "style" : "buildAndRun"
  },
  "configuredTargets" : [
    {
      "guid" : "0f0885cc5b833ce9238e7e9deaa1710e796ca69458859873b4aa050e49c58a3b"
    }
  ],
  "containerPath" : "/Users/azamataidanov/Desktop/WorkoutDiary/WorkoutDiary.xcodeproj",
  "continueBuildingAfterErrors" : false,
  "dependencyScope" : "workspace",
  "enableIndexBuildArena" : false,
  "hideShellScriptEnvironment" : false,
  "parameters" : {
    "action" : "build",
    "activeArchitecture" : "arm64",
    "activeRunDestination" : {
      "disableOnlyActiveArch" : false,
      "platform" : "iphonesimulator",
      "sdk" : "iphonesimulator17.5",
      "sdkVariant" : "iphonesimulator",
      "supportedArchitectures" : [
        "arm64",
        "x86_64"
      ],
      "targetArchitecture" : "arm64"
    },
    "arenaInfo" : {
      "buildIntermediatesPath" : "/Users/azamataidanov/Desktop/WorkoutDiary/Build/Intermediates.noindex",
      "buildProductsPath" : "/Users/azamataidanov/Desktop/WorkoutDiary/Build/Products",
      "derivedDataPath" : "/Users/azamataidanov/Desktop/WorkoutDiary",
      "indexDataStoreFolderPath" : "/Users/azamataidanov/Desktop/WorkoutDiary/WorkoutDiary-eahkqhqhdosgifextvepqdhwphzs/Index.noindex/DataStore",
      "indexEnableDataStore" : true,
      "indexPCHPath" : "/Users/azamataidanov/Desktop/WorkoutDiary/WorkoutDiary-eahkqhqhdosgifextvepqdhwphzs/Index.noindex/PrecompiledHeaders",
      "pchPath" : "/Users/azamataidanov/Desktop/WorkoutDiary/Build/Intermediates.noindex/PrecompiledHeaders"
    },
    "configurationName" : "Debug",
    "overrides" : {
      "synthesized" : {
        "table" : {
          "ASSETCATALOG_FILTER_FOR_DEVICE_MODEL" : "iPhone16,1",
          "ASSETCATALOG_FILTER_FOR_DEVICE_OS_VERSION" : "17.2",
          "ASSETCATALOG_FILTER_FOR_THINNING_DEVICE_CONFIGURATION" : "iPhone16,1",
          "BUILD_ACTIVE_RESOURCES_ONLY" : "YES",
          "ENABLE_PREVIEWS" : "NO",
          "ENABLE_XOJIT_PREVIEWS" : "NO",
          "ONLY_ACTIVE_ARCH" : "YES",
          "TARGET_DEVICE_IDENTIFIER" : "09371E09-2E7C-41F6-8D2C-72FE809F1C02",
          "TARGET_DEVICE_MODEL" : "iPhone16,1",
          "TARGET_DEVICE_OS_VERSION" : "17.2",
          "TARGET_DEVICE_PLATFORM_NAME" : "iphonesimulator"
        }
      }
    }
  },
  "schemeCommand" : "launch",
  "showNonLoggedProgress" : true,
  "useDryRun" : false,
  "useImplicitDependencies" : true,
  "useLegacyBuildLocations" : false,
  "useParallelTargets" : true
}